richdb/A.py
richdb/__init__.py
richdb/cnbin.py
richdb/cncfg.py
richdb/cnconf.py
richdb/math.py
richdb/mdict.py
richdb/model.py
richdb/pray.py
richdb/richdb.py
richdb/runlog.py
richdb/stupid.py
richdb/tests.py
richdb/utils.py
richdb/vdict.py
richdb/version.py
richdb/wull.py
richdb/yield.py
richdb/ztime.py
richdb-0.1.8.dist-info/LICENSE
richdb-0.1.8.dist-info/METADATA
richdb-0.1.8.dist-info/WHEEL
richdb-0.1.8.dist-info/top_level.txt
richdb-0.1.8.dist-info/RECORD
