Metadata-Version: 2.1
Name: richdb
Version: 0.1.8
Summary: Time,Timeseries,vdict(combine the benefits of list and dict) is designed for Timeseries problem analysis
Home-page: https://github.com/javanglee/zdb.git
Author: javang.lee
Author-email: walkbob@sina.com
Classifier: Programming Language :: Python :: 3
Classifier: License :: OSI Approved :: MIT License
Classifier: Operating System :: OS Independent
Requires-Python: >=3.6
License-File: LICENSE
Requires-Dist: rich
Requires-Dist: requests
Requires-Dist: prettytable
